aparser_async/__init__.py
aparser_async/aparser.py
aparser_async/exceptions.py
aparser_async/schemas.py
aparser_async-0.0.4.dist-info/METADATA
aparser_async-0.0.4.dist-info/WHEEL
aparser_async-0.0.4.dist-info/top_level.txt
aparser_async-0.0.4.dist-info/RECORD
