Metadata-Version: 2.2
Name: aparser-async
Version: 0.0.4
Summary: Command-line tool for recursively traversing directories to print file paths and their contents. 
Author-email: Vasilii Platon <vasia.platon@gmail.com>
Project-URL: Homepage, https://github.com/vasiaplaton/aparser-async
Project-URL: Issues, https://github.com/vasiaplaton/aparser-async/issues
Classifier: Programming Language :: Python :: 3
Classifier: License :: OSI Approved :: MIT License
Classifier: Operating System :: OS Independent
Requires-Python: >=3.8
Requires-Dist: httpx<1.0.0,>=0.20.0
Requires-Dist: pydantic<3.0.0,>=2.5.3
